{
    "/js/app.js": "/js/app.js",
    "/css/app.css": "/css/app.css",
    "/js/vueapp.js": "/js/vueapp.js",
    "/1.a79e8cef7effdd173ba8.hot-update.js": "/1.a79e8cef7effdd173ba8.hot-update.js",
    "/1.a0ca8c63ac8a7ec4944c.hot-update.js": "/1.a0ca8c63ac8a7ec4944c.hot-update.js",
    "/1.c87f4e042058b205cc0e.hot-update.js": "/1.c87f4e042058b205cc0e.hot-update.js",
    "/1.95ada215d479e50a35b5.hot-update.js": "/1.95ada215d479e50a35b5.hot-update.js",
    "/1.170e80bcf75748dea457.hot-update.js": "/1.170e80bcf75748dea457.hot-update.js",
    "/1.c56c9414640769f57e08.hot-update.js": "/1.c56c9414640769f57e08.hot-update.js",
    "/1.982f63234ad2222b7b44.hot-update.js": "/1.982f63234ad2222b7b44.hot-update.js",
    "/1.27df9bdc3352feba78c2.hot-update.js": "/1.27df9bdc3352feba78c2.hot-update.js",
    "/1.4aa7d0ae14f5af7ff135.hot-update.js": "/1.4aa7d0ae14f5af7ff135.hot-update.js",
    "/1.cd829409de93234cf7ca.hot-update.js": "/1.cd829409de93234cf7ca.hot-update.js",
    "/1.5e9f5856a0a097728c4e.hot-update.js": "/1.5e9f5856a0a097728c4e.hot-update.js",
    "/1.64188182ef8218f45ac4.hot-update.js": "/1.64188182ef8218f45ac4.hot-update.js",
    "/1.2611719c8f799523fdad.hot-update.js": "/1.2611719c8f799523fdad.hot-update.js",
    "/1.84b55b2976a838fc3d52.hot-update.js": "/1.84b55b2976a838fc3d52.hot-update.js",
    "/0.103ee9247060726606e5.hot-update.js": "/0.103ee9247060726606e5.hot-update.js",
    "/0.312aeb679155b3557f08.hot-update.js": "/0.312aeb679155b3557f08.hot-update.js",
    "/1.312aeb679155b3557f08.hot-update.js": "/1.312aeb679155b3557f08.hot-update.js",
    "/0.8fa9063d432e80086ddd.hot-update.js": "/0.8fa9063d432e80086ddd.hot-update.js",
    "/1.8fa9063d432e80086ddd.hot-update.js": "/1.8fa9063d432e80086ddd.hot-update.js",
    "/0.126f53b2f5d03e5fc474.hot-update.js": "/0.126f53b2f5d03e5fc474.hot-update.js",
    "/1.9ee212bceb9ac60b2ca5.hot-update.js": "/1.9ee212bceb9ac60b2ca5.hot-update.js",
    "/0.26c375657b4a4fd93efb.hot-update.js": "/0.26c375657b4a4fd93efb.hot-update.js",
    "/0.45e99802447c292a2067.hot-update.js": "/0.45e99802447c292a2067.hot-update.js",
    "/0.ff6db8ae0e1929da0a8d.hot-update.js": "/0.ff6db8ae0e1929da0a8d.hot-update.js",
    "/0.ea918a30f5fe0e0cda9a.hot-update.js": "/0.ea918a30f5fe0e0cda9a.hot-update.js",
    "/0.c1e43f48545b1dd88115.hot-update.js": "/0.c1e43f48545b1dd88115.hot-update.js",
    "/0.4a275117f454089448b3.hot-update.js": "/0.4a275117f454089448b3.hot-update.js",
    "/0.81bf361ff904e05368d3.hot-update.js": "/0.81bf361ff904e05368d3.hot-update.js",
    "/1.79a10ec33fb1b537457a.hot-update.js": "/1.79a10ec33fb1b537457a.hot-update.js",
    "/1.7c425b73c08ab8066baa.hot-update.js": "/1.7c425b73c08ab8066baa.hot-update.js",
    "/1.b9ef720673ee48b5ac49.hot-update.js": "/1.b9ef720673ee48b5ac49.hot-update.js",
    "/1.8d356eab81cbf612da71.hot-update.js": "/1.8d356eab81cbf612da71.hot-update.js",
    "/1.a6b8783b4afbac45b1dd.hot-update.js": "/1.a6b8783b4afbac45b1dd.hot-update.js",
    "/1.ca595bb2557c69827c9e.hot-update.js": "/1.ca595bb2557c69827c9e.hot-update.js",
    "/1.f57edf9aca60edd1a56b.hot-update.js": "/1.f57edf9aca60edd1a56b.hot-update.js",
    "/1.f069f502e3bc123ea88f.hot-update.js": "/1.f069f502e3bc123ea88f.hot-update.js",
    "/1.390d450b75d0219b7ad9.hot-update.js": "/1.390d450b75d0219b7ad9.hot-update.js",
    "/1.4ed89e3b33380def939d.hot-update.js": "/1.4ed89e3b33380def939d.hot-update.js",
    "/1.5ad89f68707152decd05.hot-update.js": "/1.5ad89f68707152decd05.hot-update.js",
    "/1.f52784de33a33b2c15e1.hot-update.js": "/1.f52784de33a33b2c15e1.hot-update.js",
    "/1.1ad3e80f1543611b908d.hot-update.js": "/1.1ad3e80f1543611b908d.hot-update.js",
    "/1.3e671f1a89bbe1116699.hot-update.js": "/1.3e671f1a89bbe1116699.hot-update.js",
    "/1.6a71d6ac426cbd542494.hot-update.js": "/1.6a71d6ac426cbd542494.hot-update.js",
    "/1.3e0b1cb6133313a7dea2.hot-update.js": "/1.3e0b1cb6133313a7dea2.hot-update.js",
    "/1.ad800ddf71775a8f23e6.hot-update.js": "/1.ad800ddf71775a8f23e6.hot-update.js",
    "/1.d2f69d9905f74570bd3e.hot-update.js": "/1.d2f69d9905f74570bd3e.hot-update.js",
    "/1.d8109d01793ad2fb5bf0.hot-update.js": "/1.d8109d01793ad2fb5bf0.hot-update.js",
    "/1.590b33a78d8dcafcc001.hot-update.js": "/1.590b33a78d8dcafcc001.hot-update.js",
    "/1.627f62d5ff3e1a0228bf.hot-update.js": "/1.627f62d5ff3e1a0228bf.hot-update.js",
    "/0.5c5af0365395f3cab0ae.hot-update.js": "/0.5c5af0365395f3cab0ae.hot-update.js",
    "/0.6f8eb267e50b490c9197.hot-update.js": "/0.6f8eb267e50b490c9197.hot-update.js",
    "/1.1252a2b4955053990b3b.hot-update.js": "/1.1252a2b4955053990b3b.hot-update.js",
    "/1.f6ea44c731f3b4413b4f.hot-update.js": "/1.f6ea44c731f3b4413b4f.hot-update.js",
    "/1.f383a537ed7c2de34f6d.hot-update.js": "/1.f383a537ed7c2de34f6d.hot-update.js",
    "/1.d6fa1ff980a7e082e54a.hot-update.js": "/1.d6fa1ff980a7e082e54a.hot-update.js",
    "/1.fd63d2cb65a7e045c0c9.hot-update.js": "/1.fd63d2cb65a7e045c0c9.hot-update.js",
    "/1.7ef34f8baa7a242cf77d.hot-update.js": "/1.7ef34f8baa7a242cf77d.hot-update.js",
    "/1.8134683b92ad6ae889b0.hot-update.js": "/1.8134683b92ad6ae889b0.hot-update.js",
    "/1.09576256a59b69c7c5a8.hot-update.js": "/1.09576256a59b69c7c5a8.hot-update.js",
    "/1.e441f010086c6bb40279.hot-update.js": "/1.e441f010086c6bb40279.hot-update.js",
    "/1.70d459ac3cf9bc0186f7.hot-update.js": "/1.70d459ac3cf9bc0186f7.hot-update.js",
    "/1.dfaa0758b4df2404abe1.hot-update.js": "/1.dfaa0758b4df2404abe1.hot-update.js",
    "/1.36de653f8bded80b8cb0.hot-update.js": "/1.36de653f8bded80b8cb0.hot-update.js",
    "/1.c42e3001c12b688df10a.hot-update.js": "/1.c42e3001c12b688df10a.hot-update.js",
    "/1.58535eef17d869fa8d42.hot-update.js": "/1.58535eef17d869fa8d42.hot-update.js",
    "/1.9b8e06ec6db8d1d9761c.hot-update.js": "/1.9b8e06ec6db8d1d9761c.hot-update.js",
    "/1.2040823e0c25d95c193a.hot-update.js": "/1.2040823e0c25d95c193a.hot-update.js",
    "/1.f7370be8d1b4327affd1.hot-update.js": "/1.f7370be8d1b4327affd1.hot-update.js",
    "/1.38fbd860735d66dde767.hot-update.js": "/1.38fbd860735d66dde767.hot-update.js",
    "/1.55483531eebd23841672.hot-update.js": "/1.55483531eebd23841672.hot-update.js",
    "/1.65c8f1e0a5f3882e987d.hot-update.js": "/1.65c8f1e0a5f3882e987d.hot-update.js",
    "/1.c7829c4de8d184c10f15.hot-update.js": "/1.c7829c4de8d184c10f15.hot-update.js",
    "/1.eed1f29d97c075230662.hot-update.js": "/1.eed1f29d97c075230662.hot-update.js",
    "/1.a11bd9fca507b6b647ed.hot-update.js": "/1.a11bd9fca507b6b647ed.hot-update.js",
    "/1.f9c26d6c0e568b2cea4c.hot-update.js": "/1.f9c26d6c0e568b2cea4c.hot-update.js",
    "/1.a1d7b64bf3063a39478d.hot-update.js": "/1.a1d7b64bf3063a39478d.hot-update.js",
    "/1.aefbe0404037d27884f7.hot-update.js": "/1.aefbe0404037d27884f7.hot-update.js",
    "/1.9a1911380baa6e0416ca.hot-update.js": "/1.9a1911380baa6e0416ca.hot-update.js",
    "/1.0e2b2ef4f5ed674ae31a.hot-update.js": "/1.0e2b2ef4f5ed674ae31a.hot-update.js",
    "/1.befa349eb468ed11d357.hot-update.js": "/1.befa349eb468ed11d357.hot-update.js",
    "/1.e11ca55e1f25367cbc2c.hot-update.js": "/1.e11ca55e1f25367cbc2c.hot-update.js",
    "/1.1051e98752235e9699f8.hot-update.js": "/1.1051e98752235e9699f8.hot-update.js",
    "/1.8ceaef039b202670ae2a.hot-update.js": "/1.8ceaef039b202670ae2a.hot-update.js",
    "/1.91a6a2253b7df7ccb381.hot-update.js": "/1.91a6a2253b7df7ccb381.hot-update.js",
    "/1.2718301ad55528b4a36a.hot-update.js": "/1.2718301ad55528b4a36a.hot-update.js",
    "/1.d2385b31eebafc5e738f.hot-update.js": "/1.d2385b31eebafc5e738f.hot-update.js",
    "/1.a3cec9ee12fe42a755aa.hot-update.js": "/1.a3cec9ee12fe42a755aa.hot-update.js",
    "/1.79a90729fe9116691559.hot-update.js": "/1.79a90729fe9116691559.hot-update.js",
    "/1.a255d03d7bdaa00b16fe.hot-update.js": "/1.a255d03d7bdaa00b16fe.hot-update.js",
    "/1.8b74cabb37c034323cd2.hot-update.js": "/1.8b74cabb37c034323cd2.hot-update.js",
    "/1.6f3628550b67c785feaa.hot-update.js": "/1.6f3628550b67c785feaa.hot-update.js",
    "/1.f1864948eb13e7763aae.hot-update.js": "/1.f1864948eb13e7763aae.hot-update.js",
    "/1.39d1ed4f006e506fba4f.hot-update.js": "/1.39d1ed4f006e506fba4f.hot-update.js",
    "/1.711b8d48c7f3c6567bd3.hot-update.js": "/1.711b8d48c7f3c6567bd3.hot-update.js",
    "/1.47013c1c72203263b8ee.hot-update.js": "/1.47013c1c72203263b8ee.hot-update.js",
    "/1.df6a142126e25e8e1c07.hot-update.js": "/1.df6a142126e25e8e1c07.hot-update.js",
    "/1.9757114955bafd449991.hot-update.js": "/1.9757114955bafd449991.hot-update.js",
    "/1.b292b99ab55ac183a024.hot-update.js": "/1.b292b99ab55ac183a024.hot-update.js",
    "/1.500b63a8eaa1b3df7b0f.hot-update.js": "/1.500b63a8eaa1b3df7b0f.hot-update.js",
    "/1.e40e00071d02039dd5d0.hot-update.js": "/1.e40e00071d02039dd5d0.hot-update.js",
    "/1.9245704ca7c982d6ca7f.hot-update.js": "/1.9245704ca7c982d6ca7f.hot-update.js",
    "/1.1d0698c2d7db704cdc0d.hot-update.js": "/1.1d0698c2d7db704cdc0d.hot-update.js",
    "/1.d2ac0a192b0abd6b0213.hot-update.js": "/1.d2ac0a192b0abd6b0213.hot-update.js",
    "/1.225e13e22a3a3ac8696e.hot-update.js": "/1.225e13e22a3a3ac8696e.hot-update.js",
    "/1.74d01436d6010dda0566.hot-update.js": "/1.74d01436d6010dda0566.hot-update.js",
    "/1.12494ef84b4efc8c114f.hot-update.js": "/1.12494ef84b4efc8c114f.hot-update.js",
    "/1.a39337cf19d1e122f53e.hot-update.js": "/1.a39337cf19d1e122f53e.hot-update.js",
    "/1.89169e12048d741d416b.hot-update.js": "/1.89169e12048d741d416b.hot-update.js",
    "/1.b550e088793043d918db.hot-update.js": "/1.b550e088793043d918db.hot-update.js"
}
